StockerMake/Stocker.py
StockerMake/StockerMake.py
StockerMake/__init__.py
StockerMake/helpers.py
StockerMake-0.0.31.dist-info/LICENSE.txt
StockerMake-0.0.31.dist-info/METADATA
StockerMake-0.0.31.dist-info/WHEEL
StockerMake-0.0.31.dist-info/entry_points.txt
StockerMake-0.0.31.dist-info/top_level.txt
StockerMake-0.0.31.dist-info/RECORD
