Metadata-Version: 2.1
Name: StockerMake
Version: 0.0.31
Summary: Modular Neural Network Protyping for Stock Market Prediction
Home-page: https://github.com/CSLukeW/StockerMake
Author: Luke Williams
Author-email: williams.luke.2001@gmail.com
License: UNKNOWN
Platform: UNKNOWN
Classifier: Programming Language :: Python :: 3
Classifier: License :: OSI Approved :: GNU Lesser General Public License v3 (LGPLv3)
Classifier: Operating System :: OS Independent
Classifier: Development Status :: 3 - Alpha
Requires-Python: >=3.6
Requires-Dist: absl-py (==0.9.0)
Requires-Dist: aiohttp (==3.6.2)
Requires-Dist: alpha-vantage (==2.2.0)
Requires-Dist: astunparse (==1.6.3)
Requires-Dist: async-timeout (==3.0.1)
Requires-Dist: attrs (==19.3.0)
Requires-Dist: cachetools (==4.1.0)
Requires-Dist: certifi (==2020.6.20)
Requires-Dist: chardet (==3.0.4)
Requires-Dist: gast (==0.3.3)
Requires-Dist: google-auth (==1.18.0)
Requires-Dist: google-auth-oauthlib (==0.4.1)
Requires-Dist: google-pasta (==0.2.0)
Requires-Dist: grpcio (==1.29.0)
Requires-Dist: h5py (==2.10.0)
Requires-Dist: idna (==2.9)
Requires-Dist: idna-ssl (==1.1.0)
Requires-Dist: importlib-metadata (==1.6.1)
Requires-Dist: joblib (==0.15.1)
Requires-Dist: Keras-Preprocessing (==1.1.2)
Requires-Dist: Markdown (==3.2.2)
Requires-Dist: matplotlib (==3.2.2)
Requires-Dist: multidict (==4.7.6)
Requires-Dist: numpy (==1.19.0)
Requires-Dist: oauthlib (==3.1.0)
Requires-Dist: opt-einsum (==3.2.1)
Requires-Dist: pandas (==1.0.5)
Requires-Dist: protobuf (==3.12.2)
Requires-Dist: pyasn1 (==0.4.8)
Requires-Dist: pyasn1-modules (==0.2.8)
Requires-Dist: python-dateutil (==2.8.1)
Requires-Dist: pytz (==2020.1)
Requires-Dist: requests (==2.24.0)
Requires-Dist: requests-oauthlib (==1.3.0)
Requires-Dist: rsa (==4.6)
Requires-Dist: scikit-learn (==0.23.1)
Requires-Dist: scipy (==1.4.1)
Requires-Dist: six (==1.15.0)
Requires-Dist: sklearn (==0.0)
Requires-Dist: tensorboard (==2.2.2)
Requires-Dist: tensorboard-plugin-wit (==1.6.0.post3)
Requires-Dist: tensorflow (==2.2.0)
Requires-Dist: tensorflow-estimator (==2.2.0)
Requires-Dist: termcolor (==1.1.0)
Requires-Dist: threadpoolctl (==2.1.0)
Requires-Dist: typing-extensions (==3.7.4.2)
Requires-Dist: urllib3 (==1.25.9)
Requires-Dist: Werkzeug (==1.0.1)
Requires-Dist: wrapt (==1.12.1)
Requires-Dist: yarl (==1.4.2)
Requires-Dist: zipp (==3.1.0)
